mendiafilescraper/__init__.py
mendiafilescraper/__main__.py
mendiafilescraper/database.py
mendiafilescraper/hasher.py
mendiafilescraper/mendia.py
mendiafilescraper/movie_scraper.py
mendiafilescraper/path_element.py
mendiafilescraper/scraper.py
mendiafilescraper-3.1.1.dist-info/LICENSE
mendiafilescraper-3.1.1.dist-info/entry_points.txt
mendiafilescraper-3.1.1.dist-info/METADATA
mendiafilescraper-3.1.1.dist-info/WHEEL
mendiafilescraper-3.1.1.dist-info/RECORD
