Metadata-Version: 2.1
Name: mendiafilescraper
Version: 3.1.1
Summary: File scrapper for clients to sync with a mendia rust application running on a server.
Home-page: https://gitlab.com/derfreak/MediaScrapper
License: LICENSE
Keywords: mendia,movies,collection
Author: Lukas Riedersberger
Author-email: lukas.riedersberger@posteo.de
Requires-Python: >=3.9
Classifier: License :: Other/Proprietary License
Classifier: Programming Language :: Python :: 3
Classifier: Programming Language :: Python :: 3.9
Classifier: Programming Language :: Python :: 3.10
Classifier: Programming Language :: Python :: 3.11
Requires-Dist: dataclasses-json (>=0.5.2,<0.6.0)
Requires-Dist: peewee (>=3.15.4,<4.0.0)
Requires-Dist: pymediainfo (>=5.0.3,<5.1.0)
Requires-Dist: requests (>=2.25.1,<2.26.0)
Requires-Dist: tmdbsimple (>=2.7.0,<2.8.0)
Requires-Dist: websockets (>=10.4,<11.0)
Project-URL: Documentation, https://gitlab.com/derfreak/MediaScrapper
Project-URL: Repository, https://gitlab.com/derfreak/MediaScrapper
